{
    "total": [
        {
            "id": "61558387105931",
            "count": 0
        },
        {
            "id": "100080635040919",
            "count": 51
        },
        {
            "id": "100038740121428",
            "count": 95
        }
    ],
    "week": [
        {
            "id": "61558387105931",
            "count": 0
        },
        {
            "id": "100080635040919",
            "count": 51
        },
        {
            "id": "100038740121428",
            "count": 95
        }
    ],
    "day": [
        {
            "id": "61558387105931",
            "count": 0
        },
        {
            "id": "100080635040919",
            "count": 51
        },
        {
            "id": "100038740121428",
            "count": 95
        }
    ],
    "time": 3
}